{"HN":[{"Title":"The murky history of moderation and how it’s shaping the future of free speech","Url":"http://www.theverge.com/2016/4/13/11387934/internet-moderator-history-youtube-facebook-reddit-censorship-free-speech","CommentUrl":"http://news.ycombinator.com/item?id=11500234"},{"Title":"Sorry, You Can’t Speed Read","Url":"http://www.nytimes.com/2016/04/17/opinion/sunday/sorry-you-cant-speed-read.html","CommentUrl":"http://news.ycombinator.com/item?id=11509160"},{"Title":"TensorFlow: Large-Scale Machine Learning on Distributed Systems (2015) [pdf]","Url":"http://download.tensorflow.org/paper/whitepaper2015.pdf","CommentUrl":"http://news.ycombinator.com/item?id=11510199"},{"Title":"In Cramped and Costly Bay Area, Cries to Build, Baby, Build","Url":"http://www.nytimes.com/2016/04/17/business/economy/san-francisco-housing-tech-boom-sf-barf.html","CommentUrl":"http://news.ycombinator.com/item?id=11510349"},{"Title":"Unix’s file durability problem","Url":"https://utcc.utoronto.ca/~cks/space/blog/unix/FileSyncProblem","CommentUrl":"http://news.ycombinator.com/item?id=11511269"},{"Title":"Phineas Fisher's account of how he took down HackingTeam","Url":"https://ghostbin.com/paste/6kho7","CommentUrl":"http://news.ycombinator.com/item?id=11512845"},{"Title":"Apple's amusingly round reuse figures","Url":"http://blog.jgc.org/2016/04/apples-amusingly-round-reuse-figures.html","CommentUrl":"http://news.ycombinator.com/item?id=11514106"},{"Title":"Ask HN: Can't concentrate to focus, until it's last minute or later","Url":"https://news.ycombinator.com/item?id=11514266","CommentUrl":"http://news.ycombinator.com/item?id=11514266"},{"Title":"Over $700k selling a premium mobile game","Url":"https://www.reddit.com/r/startups/comments/4f74dv/quit_my_full_time_corporate_job_built_an_ios_game/","CommentUrl":"http://news.ycombinator.com/item?id=11514968"},{"Title":"Ask HN: Describe your first enterprise sale","Url":"https://news.ycombinator.com/item?id=11515307","CommentUrl":"http://news.ycombinator.com/item?id=11515307"}],"GH":[{"Language":"swift","Repos":[{"Title":"BradLarson/GPUImage2","Description":"GPUImage 2 is a BSD-licensed Swift framework for GPU-accelerated video and image processing.","Url":"https://github.com/BradLarson/GPUImage2"},{"Title":"delba/TextAttributes","Description":"An easier way to compose attributed strings","Url":"https://github.com/delba/TextAttributes"},{"Title":"nakiostudio/EasyPeasy","Description":"Auto Layout made easy","Url":"https://github.com/nakiostudio/EasyPeasy"},{"Title":"shaps80/Peek","Description":"Take a Peek at your application.","Url":"https://github.com/shaps80/Peek"},{"Title":"PhamBaTho/BTNavigationDropdownMenu","Description":"The elegant dropdown menu, written in Swift, appears underneath navigation bar to display a list of related items when a user click on the navigation title.","Url":"https://github.com/PhamBaTho/BTNavigationDropdownMenu"},{"Title":"boycechang/BCColor","Description":"A lightweight but powerful color kit (Swift)","Url":"https://github.com/boycechang/BCColor"},{"Title":"vsouza/awesome-ios","Description":"A curated list of awesome iOS ecosystem, including Objective-C and Swift Projects","Url":"https://github.com/vsouza/awesome-ios"},{"Title":"Yalantis/DisplaySwitcher","Description":"Custom transition between two collection view layouts","Url":"https://github.com/Yalantis/DisplaySwitcher"},{"Title":"Alamofire/Alamofire","Description":"Elegant HTTP Networking in Swift","Url":"https://github.com/Alamofire/Alamofire"},{"Title":"Skyscanner/SkyFloatingLabelTextField","Description":"A beautiful and flexible text field control implementation of \"Float Label Pattern\". Written in Swift. As used in the Skyscanner TravelPro iOS app.","Url":"https://github.com/Skyscanner/SkyFloatingLabelTextField"},{"Title":"hyperoslo/Spots","Description":"Spots is a view controller framework that makes your setup and future development blazingly fast.","Url":"https://github.com/hyperoslo/Spots"},{"Title":"Ramotion/folding-cell","Description":"FoldingCell is an expanding content cell inspired by folding paper material","Url":"https://github.com/Ramotion/folding-cell"},{"Title":"patchthecode/JTAppleCalendar","Description":"The final Apple calendar you will ever try. Built for iOS in Swift.","Url":"https://github.com/patchthecode/JTAppleCalendar"},{"Title":"me-abhinav/NumberMorphView","Description":"A label view for displaying numbers which can transition or animate using a technique called number tweening or number morphing.","Url":"https://github.com/me-abhinav/NumberMorphView"},{"Title":"danielgindi/Charts","Description":"Beautiful charts for iOS/tvOS/OSX! The Apple side of the crossplatform MPAndroidChart.","Url":"https://github.com/danielgindi/Charts"},{"Title":"shu223/Pulsator","Description":"Pulse animation for iOS","Url":"https://github.com/shu223/Pulsator"},{"Title":"ipader/SwiftGuide","Description":"这份指南汇集了Swift语言主流学习资源，并以开发者的视角整理编排。http://dev.swiftguide.cn","Url":"https://github.com/ipader/SwiftGuide"},{"Title":"ShinCurry/Maria","Description":"an OS X app/widget for aria2 download tool.","Url":"https://github.com/ShinCurry/Maria"},{"Title":"delba/Permission","Description":"A unified API to ask for permissions on iOS","Url":"https://github.com/delba/Permission"},{"Title":"ochococo/Design-Patterns-In-Swift","Description":"Design Patterns implemented in Swift","Url":"https://github.com/ochococo/Design-Patterns-In-Swift"},{"Title":"allenwong/30DaysofSwift","Description":"A self-taught project to learn Swift.","Url":"https://github.com/allenwong/30DaysofSwift"},{"Title":"matteocrippa/awesome-swift","Description":"A collaborative list of awesome swift resources. Feel free to contribute!","Url":"https://github.com/matteocrippa/awesome-swift"},{"Title":"SwiftyJSON/SwiftyJSON","Description":"The better way to deal with JSON data in Swift","Url":"https://github.com/SwiftyJSON/SwiftyJSON"},{"Title":"Ramotion/animated-tab-bar","Description":"RAMAnimatedTabBarController is a Swift module for adding animation to tabbar items.","Url":"https://github.com/Ramotion/animated-tab-bar"},{"Title":"lyimin/EyepetizerApp","Description":"高仿开眼","Url":"https://github.com/lyimin/EyepetizerApp"}]},{"Language":"objective-c","Repos":[{"Title":"facebook/FBMemoryProfiler","Description":"iOS tool that helps with profiling iOS Memory usage.","Url":"https://github.com/facebook/FBMemoryProfiler"},{"Title":"hustlzp/xichuangzhu-ios","Description":"西窗烛 iOS App.","Url":"https://github.com/hustlzp/xichuangzhu-ios"},{"Title":"leichunfeng/LCFInfiniteScrollView","Description":"A Circular and Infinite Scroll View, Inspired by the App Store Banner View","Url":"https://github.com/leichunfeng/LCFInfiniteScrollView"},{"Title":"facebook/FBRetainCycleDetector","Description":"iOS library to help detecting retain cycles in runtime.","Url":"https://github.com/facebook/FBRetainCycleDetector"},{"Title":"Draveness/Typeset","Description":"Deal with AttributedString efficiently","Url":"https://github.com/Draveness/Typeset"},{"Title":"ChenYilong/iOS9AdaptationTips","Description":"iOS9适配系列教程（iOS9开发学习交流群：541317935）","Url":"https://github.com/ChenYilong/iOS9AdaptationTips"},{"Title":"baidao/YTXAnimations","Description":"The iOS Animation Implementation of animate.css.","Url":"https://github.com/baidao/YTXAnimations"},{"Title":"youzan/SigmaTableViewModel","Description":"","Url":"https://github.com/youzan/SigmaTableViewModel"},{"Title":"johnno1962/injectionforxcode","Description":"Runtime Code Injection for Objective-C \u0026 Swift","Url":"https://github.com/johnno1962/injectionforxcode"},{"Title":"bang590/JSPatch","Description":"JSPatch bridge Objective-C and Javascript using the Objective-C runtime. You can call any Objective-C class and method in JavaScript by just including a small engine. JSPatch is generally use for hotfix iOS App.","Url":"https://github.com/bang590/JSPatch"},{"Title":"shenAlexy/MVVM","Description":"MVVM architecture of a practice, rewrite the iOS headlines for the client（MVVM架构的一次实践，重写iOS头条客户端）","Url":"https://github.com/shenAlexy/MVVM"},{"Title":"AFNetworking/AFNetworking","Description":"A delightful networking framework for iOS, OS X, watchOS, and tvOS.","Url":"https://github.com/AFNetworking/AFNetworking"},{"Title":"gk-brown/MarkupKit","Description":"Declarative UI for iOS applications","Url":"https://github.com/gk-brown/MarkupKit"},{"Title":"BradLarson/GPUImage","Description":"An open source iOS framework for GPU-based image and video processing","Url":"https://github.com/BradLarson/GPUImage"},{"Title":"WenchaoD/FSCalendar","Description":"A superiorly awesome iOS7+ calendar control, compatible with both Objective-C and Swift2","Url":"https://github.com/WenchaoD/FSCalendar"},{"Title":"rs/SDWebImage","Description":"Asynchronous image downloader with cache support as a UIImageView category","Url":"https://github.com/rs/SDWebImage"},{"Title":"dkhamsing/open-source-ios-apps","Description":"Collaborative List of Open-Source iOS Apps","Url":"https://github.com/dkhamsing/open-source-ios-apps"},{"Title":"facebook/FBNotifications","Description":"Facebook Analytics In-App Notifications Framework","Url":"https://github.com/facebook/FBNotifications"},{"Title":"renzifeng/ZFPlayer","Description":"Based on AVPlayer, support for the horizontal screen, vertical screen (full screen playback can also lock the screen direction), the upper and lower slide to adjust the volume, the screen brightness, or so slide to adjust the playback progress.基于AVPlayer，支持横屏、竖屏（全屏播放还可锁定屏幕方向），上下滑动调节音量、屏幕亮度，左右滑动调节播放进度。","Url":"https://github.com/renzifeng/ZFPlayer"},{"Title":"CoderMJLee/MJRefresh","Description":"An easy way to use pull-to-refresh.","Url":"https://github.com/CoderMJLee/MJRefresh"},{"Title":"dzenbot/DZNEmptyDataSet","Description":"A drop-in UITableView/UICollectionView superclass category for showing empty datasets whenever the view has no content to display.","Url":"https://github.com/dzenbot/DZNEmptyDataSet"},{"Title":"gsdios/SDAutoLayout","Description":"One line of code to implement automatic layout. 一行代码搞定自动布局！支持Cell和Tableview高度自适应，Label和ScrollView内容自适应，致力于做最简单易用的AutoLayout库。The most easy way for autoLayout. Based Runtime.Auto Layout .","Url":"https://github.com/gsdios/SDAutoLayout"},{"Title":"jdg/MBProgressHUD","Description":"MBProgressHUD + Customizations","Url":"https://github.com/jdg/MBProgressHUD"},{"Title":"forkingdog/UITableView-FDTemplateLayoutCell","Description":"Template auto layout cell for automatically UITableViewCell height calculating","Url":"https://github.com/forkingdog/UITableView-FDTemplateLayoutCell"},{"Title":"SnapKit/Masonry","Description":"Harness the power of AutoLayout NSLayoutConstraints with a simplified, chainable and expressive syntax. Supports iOS and OSX Auto Layout","Url":"https://github.com/SnapKit/Masonry"}]},{"Language":"go","Repos":[{"Title":"zyedidia/micro","Description":"A modern and intuitive terminal-based text editor","Url":"https://github.com/zyedidia/micro"},{"Title":"jfrazelle/binctr","Description":"Fully static, unprivileged, self-contained, containers as executable binaries.","Url":"https://github.com/jfrazelle/binctr"},{"Title":"getlantern/lantern","Description":"Open Internet for everyone. Lantern is a free desktop application that delivers fast, reliable and secure access to the open Internet for users in censored regions. It uses a variety of techniques to stay unblocked, including P2P and domain fronting. Lantern relies on users in uncensored regions acting as access points to the open Internet.","Url":"https://github.com/getlantern/lantern"},{"Title":"docker/docker","Description":"Docker - the open-source application container engine","Url":"https://github.com/docker/docker"},{"Title":"avelino/awesome-go","Description":"A curated list of awesome Go frameworks, libraries and software","Url":"https://github.com/avelino/awesome-go"},{"Title":"kubernetes/kubernetes","Description":"Container Cluster Manager from Google","Url":"https://github.com/kubernetes/kubernetes"},{"Title":"ubuntu-core/snappy","Description":"Snappy is the software at the heart of Ubuntu Core.","Url":"https://github.com/ubuntu-core/snappy"},{"Title":"spf13/hugo","Description":"A Fast and Flexible Static Site Generator built with love in GoLang","Url":"https://github.com/spf13/hugo"},{"Title":"valyala/fasthttp","Description":"Fast HTTP package for Go. Tuned for high performance. Zero memory allocations in hot paths. Up to 10x faster than net/http","Url":"https://github.com/valyala/fasthttp"},{"Title":"itsabot/abot","Description":"Abot makes it easy and fun to build your own digital assistant, and we include everything you need to get started.","Url":"https://github.com/itsabot/abot"},{"Title":"armhold/polygen","Description":"genetic algorithm for approximating an image with polygons (Golang)","Url":"https://github.com/armhold/polygen"},{"Title":"schachmat/wego","Description":"weather app for the terminal","Url":"https://github.com/schachmat/wego"},{"Title":"mmcdole/gofeed","Description":"Parse RSS and Atom feeds in Go","Url":"https://github.com/mmcdole/gofeed"},{"Title":"golang/go","Description":"The Go programming language","Url":"https://github.com/golang/go"},{"Title":"astaxie/build-web-application-with-golang","Description":"A golang ebook intro how to build a web with golang","Url":"https://github.com/astaxie/build-web-application-with-golang"},{"Title":"future-architect/vuls","Description":"Vulnerability scanner for Linux, agentless, written in golang.","Url":"https://github.com/future-architect/vuls"},{"Title":"coreos/etcd","Description":"Distributed reliable key-value store for the most critical data of a distributed system","Url":"https://github.com/coreos/etcd"},{"Title":"gogits/gogs","Description":"Gogs (Go Git Service) is a painless self-hosted Git service.","Url":"https://github.com/gogits/gogs"},{"Title":"astaxie/beego","Description":"beego is an open-source, high-performance web framework for the Go programming language.","Url":"https://github.com/astaxie/beego"},{"Title":"mholt/caddy","Description":"Fast, cross-platform HTTP/2 web server with automatic HTTPS","Url":"https://github.com/mholt/caddy"},{"Title":"drone/drone","Description":"Drone is a Continuous Delivery platform built on Docker, written in Go","Url":"https://github.com/drone/drone"},{"Title":"schollz/find","Description":"High-precision indoor positioning framework for most wifi-enabled devices.","Url":"https://github.com/schollz/find"},{"Title":"boltdb/bolt","Description":"An embedded key/value database for Go.","Url":"https://github.com/boltdb/bolt"},{"Title":"containous/traefik","Description":"Træfɪk, a modern reverse proxy","Url":"https://github.com/containous/traefik"},{"Title":"labstack/echo","Description":"Echo is a fast and unfancy HTTP server framework for Go (Golang). Up to 10x faster than the rest.","Url":"https://github.com/labstack/echo"}]},{"Language":"javascript","Repos":[{"Title":"FreeCodeCamp/FreeCodeCamp","Description":"The https://FreeCodeCamp.com open source codebase and curriculum. Learn to code and help nonprofits.","Url":"https://github.com/FreeCodeCamp/FreeCodeCamp"},{"Title":"fbsamples/f8app","Description":"Source code of the official F8 app of 2016, powered by React Native and other Facebook open source projects.","Url":"https://github.com/fbsamples/f8app"},{"Title":"ademilter/bricklayer","Description":"Lightweight cascading grid layout library","Url":"https://github.com/ademilter/bricklayer"},{"Title":"koehlma/jaspy","Description":"a Python VM written entirely from scratch in JavaScript with some unique features","Url":"https://github.com/koehlma/jaspy"},{"Title":"thejameskyle/babel-react-optimize","Description":"A Babel preset and plugins for optimizing React code.","Url":"https://github.com/thejameskyle/babel-react-optimize"},{"Title":"akveo/blur-admin","Description":"Free Angular Bootstrap Admin Dashboard Template","Url":"https://github.com/akveo/blur-admin"},{"Title":"calvinfroedge/redux-modifiers","Description":"A collection of generic functions for writing redux reducers to operate on various data structures","Url":"https://github.com/calvinfroedge/redux-modifiers"},{"Title":"facebook/react","Description":"A declarative, efficient, and flexible JavaScript library for building user interfaces.","Url":"https://github.com/facebook/react"},{"Title":"airbnb/javascript","Description":"JavaScript Style Guide","Url":"https://github.com/airbnb/javascript"},{"Title":"aosabook/500lines","Description":"500 Lines or Less","Url":"https://github.com/aosabook/500lines"},{"Title":"facebook/react-native","Description":"A framework for building native apps with React.","Url":"https://github.com/facebook/react-native"},{"Title":"nodejs/node","Description":"Node.js JavaScript runtime","Url":"https://github.com/nodejs/node"},{"Title":"vuejs/vue","Description":"Simple yet powerful library for building modern web interfaces.","Url":"https://github.com/vuejs/vue"},{"Title":"MichaelHoste/xmoto.js","Description":"HTML5 Port of XMoto (2D Canvas + Box2D)","Url":"https://github.com/MichaelHoste/xmoto.js"},{"Title":"ParsePlatform/parse-server","Description":"Parse-compatible API server module for Node/Express","Url":"https://github.com/ParsePlatform/parse-server"},{"Title":"TryGhost/Ghost","Description":"Just a blogging platform","Url":"https://github.com/TryGhost/Ghost"},{"Title":"getify/You-Dont-Know-JS","Description":"A book series on JavaScript. @YDKJS on twitter.","Url":"https://github.com/getify/You-Dont-Know-JS"},{"Title":"mobxjs/mobx","Description":"Simple, scalable state management.","Url":"https://github.com/mobxjs/mobx"},{"Title":"mrdoob/three.js","Description":"JavaScript 3D library.","Url":"https://github.com/mrdoob/three.js"},{"Title":"hakimel/reveal.js","Description":"The HTML Presentation Framework","Url":"https://github.com/hakimel/reveal.js"},{"Title":"rnpm/rnpm","Description":"React Native Package Manager","Url":"https://github.com/rnpm/rnpm"},{"Title":"deepstreamIO/golden-layout","Description":"The ultimate Javascript layout manager","Url":"https://github.com/deepstreamIO/golden-layout"},{"Title":"mbostock/d3","Description":"A JavaScript visualization library for HTML and SVG.","Url":"https://github.com/mbostock/d3"},{"Title":"meteor/meteor","Description":"Meteor, the JavaScript App Platform","Url":"https://github.com/meteor/meteor"},{"Title":"reactjs/redux","Description":"Predictable state container for JavaScript apps","Url":"https://github.com/reactjs/redux"}]},{"Language":"ruby","Repos":[{"Title":"facebook/chef-cookbooks","Description":"Open source chef cookbooks.","Url":"https://github.com/facebook/chef-cookbooks"},{"Title":"jekyll/jekyll","Description":"Jekyll is a blog-aware, static site generator in Ruby","Url":"https://github.com/jekyll/jekyll"},{"Title":"Homebrew/brew","Description":"The missing package manager for OS X","Url":"https://github.com/Homebrew/brew"},{"Title":"square/shift","Description":"shift is an application that helps you run schema migrations on MySQL databases","Url":"https://github.com/square/shift"},{"Title":"cantino/huginn","Description":"Build agents that monitor and act on your behalf. Your agents are standing by!","Url":"https://github.com/cantino/huginn"},{"Title":"fastlane/fastlane","Description":"Connect all iOS and Android deployment tools into one streamlined workflow","Url":"https://github.com/fastlane/fastlane"},{"Title":"rails/rails","Description":"Ruby on Rails","Url":"https://github.com/rails/rails"},{"Title":"jondot/awesome-react-native","Description":"An \"awesome\" type curated list of React Native components, news, tools, and learning material","Url":"https://github.com/jondot/awesome-react-native"},{"Title":"CocoaPods/CocoaPods","Description":"The Cocoa Dependency Manager.","Url":"https://github.com/CocoaPods/CocoaPods"},{"Title":"mitchellh/vagrant","Description":"Vagrant is a tool for building and distributing development environments.","Url":"https://github.com/mitchellh/vagrant"},{"Title":"capistrano/capistrano","Description":"Remote multi-server automation tool","Url":"https://github.com/capistrano/capistrano"},{"Title":"discourse/discourse","Description":"A platform for community discussion. Free, open, simple.","Url":"https://github.com/discourse/discourse"},{"Title":"Thibaut/devdocs","Description":"API Documentation Browser","Url":"https://github.com/Thibaut/devdocs"},{"Title":"shakacode/react_on_rails","Description":"Integration of React + Webpack + Rails to build Universal (Isomorphic) Apps","Url":"https://github.com/shakacode/react_on_rails"},{"Title":"urbanadventurer/WhatWeb","Description":"Website Fingerprinter","Url":"https://github.com/urbanadventurer/WhatWeb"},{"Title":"jeremyevans/rodauth","Description":"Authentication and Account Management Framework for Rack Applications","Url":"https://github.com/jeremyevans/rodauth"},{"Title":"elastic/logstash","Description":"logstash - transport and process your logs, events, or other data","Url":"https://github.com/elastic/logstash"},{"Title":"Shopify/liquid","Description":"Liquid markup language. Safe, customer facing template language for flexible web apps.","Url":"https://github.com/Shopify/liquid"},{"Title":"github/linguist","Description":"Language Savant. If your repository's language is being reported incorrectly, send us a pull request!","Url":"https://github.com/github/linguist"},{"Title":"Shopify/shipit-engine","Description":"Deployment coordination","Url":"https://github.com/Shopify/shipit-engine"},{"Title":"bkeepers/dotenv","Description":"Loads environment variables from `.env`.","Url":"https://github.com/bkeepers/dotenv"},{"Title":"ruby/ruby","Description":"The Ruby Programming Language","Url":"https://github.com/ruby/ruby"},{"Title":"NullVoxPopuli/action_cable_client","Description":"A ruby client for interacting with Rails' ActionCable","Url":"https://github.com/NullVoxPopuli/action_cable_client"},{"Title":"Linuxbrew/linuxbrew","Description":"The Homebrew package manager for Linux","Url":"https://github.com/Linuxbrew/linuxbrew"},{"Title":"dejan/rails_panel","Description":"Chrome extension for Rails development","Url":"https://github.com/dejan/rails_panel"}]},{"Language":"python","Repos":[{"Title":"HelloZeroNet/ZeroNet","Description":"ZeroNet - Decentralized websites using Bitcoin crypto and BitTorrent network","Url":"https://github.com/HelloZeroNet/ZeroNet"},{"Title":"snare/voltron","Description":"A hacky debugger UI for hackers","Url":"https://github.com/snare/voltron"},{"Title":"donnemartin/haxor-news","Description":"A Hacker News command line interface (CLI) with autocomplete, output highlighting, and comment filtering.","Url":"https://github.com/donnemartin/haxor-news"},{"Title":"vinta/awesome-python","Description":"A curated list of awesome Python frameworks, libraries, software and resources","Url":"https://github.com/vinta/awesome-python"},{"Title":"letsencrypt/letsencrypt","Description":"This Let's Encrypt repo is an ACME client that can obtain certs and extensibly update server configurations (currently supports Apache automation, nginx support coming soon)","Url":"https://github.com/letsencrypt/letsencrypt"},{"Title":"airbnb/airflow","Description":"Airflow is a system to programmatically author, schedule and monitor data pipelines.","Url":"https://github.com/airbnb/airflow"},{"Title":"SpiderLabs/Responder","Description":"Responder is a LLMNR, NBT-NS and MDNS poisoner, with built-in HTTP/SMB/MSSQL/FTP/LDAP rogue authentication server supporting NTLMv1/NTLMv2/LMv2, Extended Security NTLMSSP and Basic HTTP authentication.","Url":"https://github.com/SpiderLabs/Responder"},{"Title":"scikit-learn/scikit-learn","Description":"scikit-learn: machine learning in Python","Url":"https://github.com/scikit-learn/scikit-learn"},{"Title":"rg3/youtube-dl","Description":"Small command-line program to download videos from YouTube.com and other video sites","Url":"https://github.com/rg3/youtube-dl"},{"Title":"soimort/you-get","Description":"Dumb downloader that scrapes the web","Url":"https://github.com/soimort/you-get"},{"Title":"airbnb/caravel","Description":"Caravel is a data exploration platform designed to be visual, intuitive, and interactive","Url":"https://github.com/airbnb/caravel"},{"Title":"scrapy/scrapy","Description":"Scrapy, a fast high-level web crawling \u0026 scraping framework for Python.","Url":"https://github.com/scrapy/scrapy"},{"Title":"alexjc/neural-doodle","Description":"Turn your two-bit doodles into fine artworks with deep neural networks! An implementation of Semantic Style Transfer.","Url":"https://github.com/alexjc/neural-doodle"},{"Title":"devttys0/binwalk","Description":"Firmware Analysis Tool","Url":"https://github.com/devttys0/binwalk"},{"Title":"pallets/flask","Description":"A microframework based on Werkzeug, Jinja2 and good intentions","Url":"https://github.com/pallets/flask"},{"Title":"josephmisiti/awesome-machine-learning","Description":"A curated list of awesome Machine Learning frameworks, libraries and software.","Url":"https://github.com/josephmisiti/awesome-machine-learning"},{"Title":"fchollet/keras","Description":"Deep Learning library for Python. Convnets, recurrent neural networks, and more. Runs on Theano and TensorFlow.","Url":"https://github.com/fchollet/keras"},{"Title":"XX-net/XX-Net","Description":"接力GoAgent翻墙工具----Anti-censorship tools","Url":"https://github.com/XX-net/XX-Net"},{"Title":"jisungk/deepjazz","Description":"Deep learning driven jazz generation using Keras \u0026 Theano!","Url":"https://github.com/jisungk/deepjazz"},{"Title":"tflearn/tflearn","Description":"Deep learning library featuring a higher-level API for TensorFlow.","Url":"https://github.com/tflearn/tflearn"},{"Title":"LiuRoy/huatian-funny","Description":"科学地分析自己的择偶观","Url":"https://github.com/LiuRoy/huatian-funny"},{"Title":"prajwalkr/SnapSudoku","Description":"Extract and solve Sudoku from an image","Url":"https://github.com/prajwalkr/SnapSudoku"},{"Title":"django/django","Description":"The Web framework for perfectionists with deadlines.","Url":"https://github.com/django/django"},{"Title":"ansible/ansible","Description":"Ansible is a radically simple IT automation platform that makes your applications and systems easier to deploy. Avoid writing scripts or custom code to deploy and update your applications— automate in a language that approaches plain English, using SSH, with no agents to install on remote systems.","Url":"https://github.com/ansible/ansible"},{"Title":"shadowsocks/shadowsocks","Description":"","Url":"https://github.com/shadowsocks/shadowsocks"}]}],"PH":[{"Name":"Nomino","Tagline":"Find a cool name for your product ","VotesCount":426,"RedirectUrl":"https://www.producthunt.com/r/edaf57031ed640/59281?app_id=2276"},{"Name":"ZEI°","Tagline":"Revolutionary time tracking device","VotesCount":272,"RedirectUrl":"https://www.producthunt.com/r/35c4ba2d2824fe/59237?app_id=2276"},{"Name":"YC Interview Practice App","Tagline":"Get asked YC questions by Sam Altman","VotesCount":220,"RedirectUrl":"https://www.producthunt.com/r/df92d0402a4c13/59319?app_id=2276"},{"Name":"Spaces","Tagline":"A showcase of curated Amazon products from inspiring spaces.","VotesCount":125,"RedirectUrl":"https://www.producthunt.com/r/1a0f11710bb146/59031?app_id=2276"},{"Name":"Material Colors","Tagline":"A tool for material design colors","VotesCount":134,"RedirectUrl":"https://www.producthunt.com/r/23369378cc12e8/59276?app_id=2276"},{"Name":"The Atlas of Economic Complexity","Tagline":"Beautiful graphics of imports and exports by country","VotesCount":125,"RedirectUrl":"https://www.producthunt.com/r/afd8ad7e3838a9/59288?app_id=2276"},{"Name":"a.placebetween.us","Tagline":"Find a meeting point based on place type","VotesCount":105,"RedirectUrl":"https://www.producthunt.com/r/4510bea03ce3f5/56478?app_id=2276"},{"Name":"Favorr","Tagline":"A place for app developers to give and receive reviews.","VotesCount":91,"RedirectUrl":"https://www.producthunt.com/r/219f899d450516/57449?app_id=2276"},{"Name":"yEd","Tagline":"Powerful free app for generating high-quality diagrams","VotesCount":60,"RedirectUrl":"https://www.producthunt.com/r/63fcb29fcabe54/59327?app_id=2276"},{"Name":"The 64","Tagline":"Re-imagining of the original home computer, the Commodore C6","VotesCount":61,"RedirectUrl":"https://www.producthunt.com/r/1b27e5b5fc7325/59315?app_id=2276"},{"Name":"JetHop","Tagline":"Discover your next vacation without needing a destination!","VotesCount":39,"RedirectUrl":"https://www.producthunt.com/r/4ae776a1ad085d/59338?app_id=2276"},{"Name":"Sight Reading Machine","Tagline":"Computer generated music for sight reading practice","VotesCount":50,"RedirectUrl":"https://www.producthunt.com/r/4264333a343deb/59277?app_id=2276"},{"Name":"Haxor News","Tagline":"A Hacker News command line interface","VotesCount":45,"RedirectUrl":"https://www.producthunt.com/r/c55ff990afee04/59317?app_id=2276"},{"Name":"The New Yorker Today","Tagline":"Quality journalism \u0026 writing; still all about the cartoons! ","VotesCount":22,"RedirectUrl":"https://www.producthunt.com/r/dbd38e78f06130/59130?app_id=2276"},{"Name":"The Martin Jetpack","Tagline":"Fly the dream","VotesCount":32,"RedirectUrl":"https://www.producthunt.com/r/06dc34b5c8abfd/59295?app_id=2276"},{"Name":"Vanished Aeroplanes","Tagline":"Map of aircraft which have gone missing around the world","VotesCount":31,"RedirectUrl":"https://www.producthunt.com/r/f0587404ce66c4/59306?app_id=2276"},{"Name":"Blast","Tagline":"Share photos and videos with people around you","VotesCount":16,"RedirectUrl":"https://www.producthunt.com/r/1b02a66040fe46/59346?app_id=2276"},{"Name":"Wallapatta","Tagline":"Like Markdown, but inspired by handouts of Edward R. Tufte","VotesCount":24,"RedirectUrl":"https://www.producthunt.com/r/c394aeedae5e32/59316?app_id=2276"},{"Name":"ThinkThinly","Tagline":"Motivational text messages sent at workout times.","VotesCount":24,"RedirectUrl":"https://www.producthunt.com/r/b9bf49140ddfe9/59296?app_id=2276"},{"Name":"Git Random","Tagline":"Chrome extension to replace new tab with random github user","VotesCount":17,"RedirectUrl":"https://www.producthunt.com/r/93d244b250d7e0/59262?app_id=2276"}]}