{"HN":[{"Title":"The Sign Up with Google Mistake You Can't Fix","Url":"https://maltheborch.com/2016/03/the-sign-up-with-google-mistake-you-can%27t-fix.html","CommentUrl":"http://news.ycombinator.com/item?id=11204706"},{"Title":"How to Deploy Software","Url":"https://zachholman.com/posts/deploying-software","CommentUrl":"http://news.ycombinator.com/item?id=11204736"},{"Title":"FBI’s Comey Concedes Mistake Was Made Over iPhone in San Bernardino Case","Url":"http://www.wsj.com/articles/fbis-comey-concedes-mistake-was-made-over-iphone-in-terror-case-1456862127","CommentUrl":"http://news.ycombinator.com/item?id=11205787"},{"Title":"Ten lessons I wish I had learned before teaching differential equations (1997) [pdf]","Url":"http://www.math.toronto.edu/lgoldmak/Rota.pdf","CommentUrl":"http://news.ycombinator.com/item?id=11207183"},{"Title":"I’ve Had a Cyberstalker Since I Was 12","Url":"https://backchannel.com/i-ve-had-a-cyberstalker-since-i-was-12-384ea9853b79","CommentUrl":"http://news.ycombinator.com/item?id=11207626"},{"Title":"Kofi Annan on Why It's Time to Legalize Drugs","Url":"http://www.spiegel.de/international/world/kofi-annan-on-why-drug-bans-are-ineffective-a-1078402.html","CommentUrl":"http://news.ycombinator.com/item?id=11209025"},{"Title":"Kanye West caught using Pirate Bay to download music software","Url":"http://arstechnica.co.uk/business/2016/03/kanye-west-caught-using-pirate-bay-to-download-music-software/","CommentUrl":"http://news.ycombinator.com/item?id=11209707"},{"Title":"Go channels are bad","Url":"http://www.jtolds.com/writing/2016/03/go-channels-are-bad-and-you-should-feel-bad/","CommentUrl":"http://news.ycombinator.com/item?id=11210578"},{"Title":"Eric Schmidt to head new Pentagon innovation board","Url":"http://www.reuters.com/article/us-usa-military-innovation-idUSKCN0W421V","CommentUrl":"http://news.ycombinator.com/item?id=11210836"},{"Title":"Nanex Gets $700k Whistleblower Award from SEC","Url":"http://www.nanex.net/aqck2/4712.html","CommentUrl":"http://news.ycombinator.com/item?id=11211093"}],"GH":[{"Language":"swift","Repos":[{"Title":"storehouse/Advance","Description":"A powerful animation framework for iOS.","Url":"https://github.com/storehouse/Advance"},{"Title":"hollance/swift-algorithm-club","Description":"Algorithms and data structures in Swift, with explanations!","Url":"https://github.com/hollance/swift-algorithm-club"},{"Title":"lorentey/BTree","Description":"Fast ordered collections for Swift using in-memory B-trees","Url":"https://github.com/lorentey/BTree"},{"Title":"jeffh/Snorlax","Description":"The ultimate lazy library. An example for being a good library citizen in Swift.","Url":"https://github.com/jeffh/Snorlax"},{"Title":"amayne/SwiftString","Description":"A comprehensive, lightweight string extension for Swift","Url":"https://github.com/amayne/SwiftString"},{"Title":"IBM-Swift/Kitura","Description":"Web framework and HTTP server for Swift","Url":"https://github.com/IBM-Swift/Kitura"},{"Title":"mxcl/PromiseKit","Description":"Promises for iOS and OS X","Url":"https://github.com/mxcl/PromiseKit"},{"Title":"Zewo/Zewo","Description":"Open source libraries to help you build modern and blazing fast server software","Url":"https://github.com/Zewo/Zewo"},{"Title":"vsouza/awesome-ios","Description":"A curated list of awesome iOS ecosystem, including Objective-C and Swift Projects","Url":"https://github.com/vsouza/awesome-ios"},{"Title":"b3ll/SwiftyGestureRecognition","Description":"Aids with prototyping UIGestureRecognizers in Xcode Playgrounds","Url":"https://github.com/b3ll/SwiftyGestureRecognition"},{"Title":"Alamofire/Alamofire","Description":"Elegant HTTP Networking in Swift","Url":"https://github.com/Alamofire/Alamofire"},{"Title":"matteocrippa/awesome-swift","Description":"A collaborative list of awesome swift resources. Feel free to contribute!","Url":"https://github.com/matteocrippa/awesome-swift"},{"Title":"PerfectlySoft/Perfect","Description":"Server-side Swift. The Perfect library, application server, connectors and example apps. (For mobile back-end development, website and web app development, and more...)","Url":"https://github.com/PerfectlySoft/Perfect"},{"Title":"necolt/Swifton","Description":"A Ruby on Rails inspired Web Framework for Swift that runs on Linux and OS X","Url":"https://github.com/necolt/Swifton"},{"Title":"danielgindi/ios-charts","Description":"An iOS port of the beautiful MPAndroidChart. - Beautiful charts for iOS apps!","Url":"https://github.com/danielgindi/ios-charts"},{"Title":"movielala/TVOSSlideViewController","Description":"Container view controller with left and right drawer controlling by pan gesture for tvOS.","Url":"https://github.com/movielala/TVOSSlideViewController"},{"Title":"ReactiveX/RxSwift","Description":"Reactive Programming in Swift","Url":"https://github.com/ReactiveX/RxSwift"},{"Title":"movielala/TVOSButton","Description":"Missing button component for tvos","Url":"https://github.com/movielala/TVOSButton"},{"Title":"bestswifter/MySampleCode","Description":"这个项目用于存储我博客中的demo","Url":"https://github.com/bestswifter/MySampleCode"},{"Title":"SwiftyBeaver/SwiftyBeaver","Description":"Colorful, lightweight \u0026 fast logging in Swift 2","Url":"https://github.com/SwiftyBeaver/SwiftyBeaver"},{"Title":"thoughtbot/Markoff","Description":"A light-weight Markdown (CommonMark) previewer for OSX.","Url":"https://github.com/thoughtbot/Markoff"},{"Title":"Wl201314/MJianshu","Description":"Swift高仿简书（jianshu），不定时更新－－－欢迎Star","Url":"https://github.com/Wl201314/MJianshu"},{"Title":"SwiftyJSON/SwiftyJSON","Description":"The better way to deal with JSON data in Swift","Url":"https://github.com/SwiftyJSON/SwiftyJSON"},{"Title":"Ramotion/circle-menu","Description":"CircleMenu is a simple, elegant menu with a circular layout.","Url":"https://github.com/Ramotion/circle-menu"},{"Title":"SnapKit/SnapKit","Description":"A Swift Autolayout DSL for iOS \u0026 OS X","Url":"https://github.com/SnapKit/SnapKit"}]},{"Language":"objective-c","Repos":[{"Title":"ibireme/YYKit","Description":"A collection of iOS components.","Url":"https://github.com/ibireme/YYKit"},{"Title":"dustturtle/RealReachability","Description":"We need to observe the REAL reachability of network. That's what RealReachability do.","Url":"https://github.com/dustturtle/RealReachability"},{"Title":"AFNetworking/AFNetworking","Description":"A delightful networking framework for iOS, OS X, watchOS, and tvOS.","Url":"https://github.com/AFNetworking/AFNetworking"},{"Title":"ReactiveCocoa/ReactiveCocoa","Description":"Streams of values over time","Url":"https://github.com/ReactiveCocoa/ReactiveCocoa"},{"Title":"jiachenmu/Swift-BanTang","Description":"这个开源项目为半糖，[官网➡](http://www.ibantang.com),类似于美丽说，一款电商App，使用语言:Swift2.0,开发工具: Xcode 7.1,纯代码开发,耗时两个多月，数据为本地数据，用Charles进行抓包","Url":"https://github.com/jiachenmu/Swift-BanTang"},{"Title":"google/EarlGrey","Description":"iOS UI Automation Test Framework","Url":"https://github.com/google/EarlGrey"},{"Title":"suifengqjn/TBPlayer","Description":"视频边下边播播，把播放器播放过的数据流缓存到本地，支持拖动。采用avplayer","Url":"https://github.com/suifengqjn/TBPlayer"},{"Title":"rs/SDWebImage","Description":"Asynchronous image downloader with cache support as a UIImageView category","Url":"https://github.com/rs/SDWebImage"},{"Title":"bang590/JSPatch","Description":"JSPatch bridge Objective-C and Javascript using the Objective-C runtime. You can call any Objective-C class and method in JavaScript by just including a small engine. JSPatch is generally use for hotfix iOS App.","Url":"https://github.com/bang590/JSPatch"},{"Title":"xhzengAIB/TagView","Description":"High efficiency Tag components.","Url":"https://github.com/xhzengAIB/TagView"},{"Title":"dsxNiubility/SXNews","Description":"High imitation Neteasy News. (include list,detail,photoset,weather,feedback)","Url":"https://github.com/dsxNiubility/SXNews"},{"Title":"BradLarson/GPUImage","Description":"An open source iOS framework for GPU-based image and video processing","Url":"https://github.com/BradLarson/GPUImage"},{"Title":"gsdios/SDAutoLayout","Description":"One line of code to implement automatic layout. 一行代码搞定自动布局！支持Cell和Tableview高度自适应，Label和ScrollView内容自适应，致力于做最简单易用的AutoLayout库。The most easy way for autoLayout. Based Runtime.Auto Layout .","Url":"https://github.com/gsdios/SDAutoLayout"},{"Title":"netyouli/WHC_AutoLayoutKit","Description":"致力打造使用最简单功能最强大的自动布局开源库","Url":"https://github.com/netyouli/WHC_AutoLayoutKit"},{"Title":"ViccAlexander/Chameleon","Description":"Flat Color Framework for iOS (Obj-C \u0026 Swift)","Url":"https://github.com/ViccAlexander/Chameleon"},{"Title":"onevcat/VVDocumenter-Xcode","Description":"Xcode plug-in which helps you write documentation comment easier, for both Objective-C and Swift.","Url":"https://github.com/onevcat/VVDocumenter-Xcode"},{"Title":"git-up/GitUp","Description":"The Git interface you've been missing all your life has finally arrived.","Url":"https://github.com/git-up/GitUp"},{"Title":"Zepo/MLeaksFinder","Description":"Find memory leaks in your iOS app at develop time.","Url":"https://github.com/Zepo/MLeaksFinder"},{"Title":"marcuswestin/WebViewJavascriptBridge","Description":"An iOS/OSX bridge for sending messages between Obj-C and JavaScript in UIWebViews/WebViews","Url":"https://github.com/marcuswestin/WebViewJavascriptBridge"},{"Title":"zhengwenming/WMPlayer","Description":"WMPlayer视频播放器，AVPlayer的封装，继承UIView，想怎么玩就怎么玩。支持播放mp4、m3u8、3gp、mov，网络和本地视频同时支持。全屏和小屏播放同时支持。自动感应旋转屏幕。","Url":"https://github.com/zhengwenming/WMPlayer"},{"Title":"500px/greedo-layout-for-ios","Description":"Full aspect ratio grid layout for iOS","Url":"https://github.com/500px/greedo-layout-for-ios"},{"Title":"Aufree/trip-to-iOS","Description":"A curated list of delightful iOS resources.","Url":"https://github.com/Aufree/trip-to-iOS"},{"Title":"SVProgressHUD/SVProgressHUD","Description":"A clean and lightweight progress HUD for your iOS and tvOS app.","Url":"https://github.com/SVProgressHUD/SVProgressHUD"},{"Title":"dkhamsing/open-source-ios-apps","Description":"Collaborative List of Open-Source iOS Apps","Url":"https://github.com/dkhamsing/open-source-ios-apps"},{"Title":"leichunfeng/MVVMReactiveCocoa","Description":"GitBucket iOS App","Url":"https://github.com/leichunfeng/MVVMReactiveCocoa"}]},{"Language":"go","Repos":[{"Title":"getlantern/lantern","Description":"Open Internet for everyone. Lantern is a free desktop application that delivers fast, reliable and secure access to the open Internet for users in censored regions. It uses a variety of techniques to stay unblocked, including P2P and domain fronting. Lantern relies on users in uncensored regions acting as access points to the open Internet.","Url":"https://github.com/getlantern/lantern"},{"Title":"golang/go","Description":"The Go programming language","Url":"https://github.com/golang/go"},{"Title":"docker/docker","Description":"Docker - the open-source application container engine","Url":"https://github.com/docker/docker"},{"Title":"avelino/awesome-go","Description":"A curated list of awesome Go frameworks, libraries and software","Url":"https://github.com/avelino/awesome-go"},{"Title":"fogleman/gg","Description":"Go Graphics - 2D rendering in Go with a simple API.","Url":"https://github.com/fogleman/gg"},{"Title":"micro/micro","Description":"A microservice toolkit","Url":"https://github.com/micro/micro"},{"Title":"h2non/gock","Description":"Versatile HTTP mocking made easy for Go ༼ʘ̚ل͜ʘ̚༽","Url":"https://github.com/h2non/gock"},{"Title":"msoap/go-carpet","Description":"go-carpet - show test coverage for Go source files","Url":"https://github.com/msoap/go-carpet"},{"Title":"grafana/grafana","Description":"Gorgeous metric viz, dashboards \u0026 editors for Graphite, InfluxDB \u0026 OpenTSDB","Url":"https://github.com/grafana/grafana"},{"Title":"gogits/gogs","Description":"Gogs (Go Git Service) is a painless self-hosted Git service.","Url":"https://github.com/gogits/gogs"},{"Title":"fanux/lhttp","Description":"Go websocket framework, build your IM server in 5 minute!","Url":"https://github.com/fanux/lhttp"},{"Title":"kubernetes/kubernetes","Description":"Container Cluster Manager from Google","Url":"https://github.com/kubernetes/kubernetes"},{"Title":"junegunn/fzf","Description":"A command-line fuzzy finder written in Go","Url":"https://github.com/junegunn/fzf"},{"Title":"lukasmartinelli/pgclimb","Description":"Export data from PostgreSQL into different data formats","Url":"https://github.com/lukasmartinelli/pgclimb"},{"Title":"go-kit/kit","Description":"A standard library for microservices.","Url":"https://github.com/go-kit/kit"},{"Title":"abiosoft/dockward","Description":"Port forwarding tool for Docker containers","Url":"https://github.com/abiosoft/dockward"},{"Title":"gin-gonic/gin","Description":"Gin is a HTTP web framework written in Go (Golang). It features a Martini-like API with much better performance -- up to 40 times faster. If you need smashing performance, get yourself some Gin.","Url":"https://github.com/gin-gonic/gin"},{"Title":"influxdata/influxdb","Description":"Scalable datastore for metrics, events, and real-time analytics","Url":"https://github.com/influxdata/influxdb"},{"Title":"henrylee2cn/pholcus","Description":"[爬虫框架 (golang)] Pholcus（幽灵蛛）是一款纯Go语言编写的高并发、分布式、重量级爬虫软件，支持单机、服务端、客户端三种运行模式，拥有Web、GUI、命令行三种操作界面；规则简单灵活、批量任务并发、输出方式丰富（mysql/mongodb/csv/excel等）、有大量Demo共享；同时她还支持横纵向两种抓取模式，支持模拟登录和任务暂停、取消等一系列高级功能。","Url":"https://github.com/henrylee2cn/pholcus"},{"Title":"h2non/gentleman","Description":"Full-featured plugin-driven HTTP client toolkit for Go (͡° ͜ʖ ͡°)","Url":"https://github.com/h2non/gentleman"},{"Title":"schachmat/wego","Description":"weather app for the terminal","Url":"https://github.com/schachmat/wego"},{"Title":"astaxie/build-web-application-with-golang","Description":"A golang ebook intro how to build a web with golang","Url":"https://github.com/astaxie/build-web-application-with-golang"},{"Title":"spf13/hugo","Description":"A Fast and Flexible Static Site Generator built with love in GoLang","Url":"https://github.com/spf13/hugo"},{"Title":"derekparker/delve","Description":"Delve is a debugger for the Go programming language.","Url":"https://github.com/derekparker/delve"},{"Title":"hashicorp/terraform","Description":"Terraform is a tool for building, changing, and combining infrastructure safely and efficiently.","Url":"https://github.com/hashicorp/terraform"}]},{"Language":"javascript","Repos":[{"Title":"hiloteam/Hilo","Description":"A Cross-end HTML5 Game development solution developed by Alibaba Group","Url":"https://github.com/hiloteam/Hilo"},{"Title":"geeeeeeeeek/electronic-wechat","Description":"A better WeChat client on Mac OS X and Linux.","Url":"https://github.com/geeeeeeeeek/electronic-wechat"},{"Title":"FreeCodeCamp/FreeCodeCamp","Description":"The http://FreeCodeCamp.com open source codebase and curriculum. Learn to code and help nonprofits.","Url":"https://github.com/FreeCodeCamp/FreeCodeCamp"},{"Title":"tripit/slate","Description":"Beautiful static documentation for your API","Url":"https://github.com/tripit/slate"},{"Title":"usablica/intro.js","Description":"A better way for new feature introduction and step-by-step users guide for your website and project.","Url":"https://github.com/usablica/intro.js"},{"Title":"dthree/cash","Description":"Cross-platform Linux without the suck","Url":"https://github.com/dthree/cash"},{"Title":"airbnb/enzyme","Description":"JavaScript Testing utilities for React","Url":"https://github.com/airbnb/enzyme"},{"Title":"xiekw2010/react-native-gitfeed","Description":"Yet another Github client written with react-native.","Url":"https://github.com/xiekw2010/react-native-gitfeed"},{"Title":"sqren/fb-sleep-stats","Description":"Use Facebook to track your friends’ sleeping habits","Url":"https://github.com/sqren/fb-sleep-stats"},{"Title":"typicode/hotel","Description":"local .dev domains for everyone and more!","Url":"https://github.com/typicode/hotel"},{"Title":"matthewmueller/socrates","Description":"Small (12kb), batteries-included redux stack to reduce boilerplate and promote good habits.","Url":"https://github.com/matthewmueller/socrates"},{"Title":"appbaseio/dejaVu","Description":"A modern Elasticsearch data browser","Url":"https://github.com/appbaseio/dejaVu"},{"Title":"javve/list.js","Description":"The perfect library for adding search, sort, filters and flexibility to tables, lists and various HTML elements. Built to be invisible and work on existing HTML.","Url":"https://github.com/javve/list.js"},{"Title":"airbnb/javascript","Description":"JavaScript Style Guide","Url":"https://github.com/airbnb/javascript"},{"Title":"facebook/react","Description":"A declarative, efficient, and flexible JavaScript library for building user interfaces.","Url":"https://github.com/facebook/react"},{"Title":"getify/You-Dont-Know-JS","Description":"A book series on JavaScript. @YDKJS on twitter.","Url":"https://github.com/getify/You-Dont-Know-JS"},{"Title":"santinic/how2","Description":"stackoverflow from the terminal","Url":"https://github.com/santinic/how2"},{"Title":"desandro/arpeggiator","Description":"Web audio arpeggiator","Url":"https://github.com/desandro/arpeggiator"},{"Title":"angular/angular.js","Description":"HTML enhanced for web apps","Url":"https://github.com/angular/angular.js"},{"Title":"mjackson/http-client","Description":"Compose HTTP clients using JavaScript's fetch API","Url":"https://github.com/mjackson/http-client"},{"Title":"callmecavs/bricks.js","Description":"A blazing fast masonry layout generator for fixed width elements.","Url":"https://github.com/callmecavs/bricks.js"},{"Title":"scottwoodall/django-react-template","Description":"Django \u0026 React Template For Building Web Applications","Url":"https://github.com/scottwoodall/django-react-template"},{"Title":"ParsePlatform/parse-server","Description":"Parse-compatible API server module for Node/Express","Url":"https://github.com/ParsePlatform/parse-server"},{"Title":"reactjs/redux","Description":"Predictable state container for JavaScript apps","Url":"https://github.com/reactjs/redux"},{"Title":"nodejs/node","Description":"Node.js JavaScript runtime","Url":"https://github.com/nodejs/node"}]},{"Language":"ruby","Repos":[{"Title":"molybdenum-99/reality","Description":"Comprehensive data proxy to knowledge about real world","Url":"https://github.com/molybdenum-99/reality"},{"Title":"westonganger/spreadsheet_architect","Description":"SpreadsheetArchitect lets you turn any activerecord relation or ruby object collection into a XLSX, ODS, or CSV spreadsheet","Url":"https://github.com/westonganger/spreadsheet_architect"},{"Title":"rails/rails","Description":"Ruby on Rails","Url":"https://github.com/rails/rails"},{"Title":"Homebrew/homebrew","Description":"The missing package manager for OS X.","Url":"https://github.com/Homebrew/homebrew"},{"Title":"github/scientist","Description":"A Ruby library for carefully refactoring critical paths.","Url":"https://github.com/github/scientist"},{"Title":"jondot/awesome-react-native","Description":"An \"awesome\" type curated list of React Native components, news, tools, and learning material","Url":"https://github.com/jondot/awesome-react-native"},{"Title":"jekyll/jekyll","Description":"Jekyll is a blog-aware, static site generator in Ruby","Url":"https://github.com/jekyll/jekyll"},{"Title":"fastlane/fastlane","Description":"Connect all iOS deployment tools into one streamlined workflow","Url":"https://github.com/fastlane/fastlane"},{"Title":"apneadiving/waterfall","Description":"A slice of functional programming to chain ruby services and blocks. Make them flow!","Url":"https://github.com/apneadiving/waterfall"},{"Title":"shakacode/react_on_rails","Description":"Integration of React + Webpack + Rails to build Universal (Isomorphic) Apps","Url":"https://github.com/shakacode/react_on_rails"},{"Title":"mitchellh/vagrant","Description":"Vagrant is a tool for building and distributing development environments.","Url":"https://github.com/mitchellh/vagrant"},{"Title":"discourse/discourse","Description":"A platform for community discussion. Free, open, simple.","Url":"https://github.com/discourse/discourse"},{"Title":"FetLife/rollout","Description":"Feature flippers.","Url":"https://github.com/FetLife/rollout"},{"Title":"realm/jazzy","Description":"Soulful docs for Swift \u0026 Objective-C","Url":"https://github.com/realm/jazzy"},{"Title":"caskroom/homebrew-cask","Description":"A CLI workflow for the administration of Mac applications distributed as binaries","Url":"https://github.com/caskroom/homebrew-cask"},{"Title":"gitlabhq/gitlabhq","Description":"GitLab is version control for your server","Url":"https://github.com/gitlabhq/gitlabhq"},{"Title":"Thibaut/devdocs","Description":"API Documentation Browser","Url":"https://github.com/Thibaut/devdocs"},{"Title":"bbatsov/rubocop","Description":"A Ruby static code analyzer, based on the community Ruby style guide.","Url":"https://github.com/bbatsov/rubocop"},{"Title":"Shopify/liquid","Description":"Liquid markup language. Safe, customer facing template language for flexible web apps.","Url":"https://github.com/Shopify/liquid"},{"Title":"kilimchoi/engineering-blogs","Description":"A curated list of engineering blogs","Url":"https://github.com/kilimchoi/engineering-blogs"},{"Title":"rapid7/metasploit-framework","Description":"Metasploit Framework","Url":"https://github.com/rapid7/metasploit-framework"},{"Title":"fastlane/screengrab","Description":"Automated localized screenshots of your Android app on every device","Url":"https://github.com/fastlane/screengrab"},{"Title":"twbs/bootstrap-sass","Description":"Official Sass port of Bootstrap 2 and 3.","Url":"https://github.com/twbs/bootstrap-sass"},{"Title":"deadlyvipers/dojo_rules","Description":"","Url":"https://github.com/deadlyvipers/dojo_rules"},{"Title":"sketchplugins/plugin-directory","Description":"A semi-official directory of plugins, hosted in GitHub","Url":"https://github.com/sketchplugins/plugin-directory"}]},{"Language":"python","Repos":[{"Title":"HelloZeroNet/ZeroNet","Description":"ZeroNet - Decentralized websites using Bitcoin crypto and BitTorrent network","Url":"https://github.com/HelloZeroNet/ZeroNet"},{"Title":"programthink/zhao","Description":"【编程随想】整理的《太子党关系网络》，专门揭露赵国的权贵","Url":"https://github.com/programthink/zhao"},{"Title":"nimia/public_drown_scanner","Description":"","Url":"https://github.com/nimia/public_drown_scanner"},{"Title":"danilovazb/GitMiner","Description":"Tool for advanced mining for content on Github","Url":"https://github.com/danilovazb/GitMiner"},{"Title":"jkbrzt/httpie","Description":"CLI HTTP client; user-friendly cURL replacement featuring intuitive UI, JSON support, syntax highlighting, wget-like downloads, extensions, etc.","Url":"https://github.com/jkbrzt/httpie"},{"Title":"thomasmesnard/DeepMind-Teaching-Machines-to-Read-and-Comprehend","Description":"Implementation of \"Teaching Machines to Read and Comprehend\" proposed by Google DeepMind","Url":"https://github.com/thomasmesnard/DeepMind-Teaching-Machines-to-Read-and-Comprehend"},{"Title":"XX-net/XX-Net","Description":"接力GoAgent翻墙工具----Anti-censorship tools","Url":"https://github.com/XX-net/XX-Net"},{"Title":"rnevius/minimal-django","Description":"Because Django can be nearly as simple as Flask","Url":"https://github.com/rnevius/minimal-django"},{"Title":"rhiever/datacleaner","Description":"A Python tool that automatically cleans data sets and readies them for analysis.","Url":"https://github.com/rhiever/datacleaner"},{"Title":"letsencrypt/letsencrypt","Description":"This Let's Encrypt repo is an ACME client that can obtain certs and extensibly update server configurations (currently supports Apache automation, nginx support coming soon)","Url":"https://github.com/letsencrypt/letsencrypt"},{"Title":"josephmisiti/awesome-machine-learning","Description":"A curated list of awesome Machine Learning frameworks, libraries and software.","Url":"https://github.com/josephmisiti/awesome-machine-learning"},{"Title":"vinta/awesome-python","Description":"A curated list of awesome Python frameworks, libraries and software","Url":"https://github.com/vinta/awesome-python"},{"Title":"ansible/ansible","Description":"Ansible is a radically simple IT automation platform that makes your applications and systems easier to deploy. Avoid writing scripts or custom code to deploy and update your applications— automate in a language that approaches plain English, using SSH, with no agents to install on remote systems.","Url":"https://github.com/ansible/ansible"},{"Title":"scikit-learn/scikit-learn","Description":"scikit-learn: machine learning in Python","Url":"https://github.com/scikit-learn/scikit-learn"},{"Title":"newsdev/elex","Description":"A wrapper for the AP v2 Elections API.","Url":"https://github.com/newsdev/elex"},{"Title":"nvie/pip-tools","Description":"A set of tools to keep your pinned Python dependencies fresh.","Url":"https://github.com/nvie/pip-tools"},{"Title":"mitsuhiko/flask","Description":"A microframework based on Werkzeug, Jinja2 and good intentions","Url":"https://github.com/mitsuhiko/flask"},{"Title":"rg3/youtube-dl","Description":"Small command-line program to download videos from YouTube.com and other video sites","Url":"https://github.com/rg3/youtube-dl"},{"Title":"gi0baro/weppy","Description":"The web framework for humans","Url":"https://github.com/gi0baro/weppy"},{"Title":"django/django","Description":"The Web framework for perfectionists with deadlines.","Url":"https://github.com/django/django"},{"Title":"Urinx/WeixinBot","Description":"网页版微信API，包含终端版微信及微信机器人","Url":"https://github.com/Urinx/WeixinBot"},{"Title":"gravmatt/py-term","Description":"Python module to style terminal output, moving and positioning the cursor.","Url":"https://github.com/gravmatt/py-term"},{"Title":"scrapy/scrapy","Description":"Scrapy, a fast high-level web crawling \u0026 scraping framework for Python.","Url":"https://github.com/scrapy/scrapy"},{"Title":"fchollet/keras","Description":"Deep Learning library for Python. Convnets, recurrent neural networks, and more. Runs on Theano and TensorFlow.","Url":"https://github.com/fchollet/keras"},{"Title":"spinnaker/spinnaker","Description":"Spinnaker is an open source, multi-cloud continuous delivery platform for releasing software changes with high velocity and confidence.","Url":"https://github.com/spinnaker/spinnaker"}]}],"PH":[{"Name":"Calls on Slack","Tagline":"Make voice calls in Slack","VotesCount":1073,"RedirectUrl":"https://www.producthunt.com/r/fbae0e7ce597fc/53628?app_id=2276"},{"Name":"Intro","Tagline":"LinkedIn for Slack","VotesCount":484,"RedirectUrl":"https://www.producthunt.com/r/fdf4260340c6c0/53657?app_id=2276"},{"Name":"DJI Phantom 4","Tagline":"Can dodge obstacles and track humans.","VotesCount":469,"RedirectUrl":"https://www.producthunt.com/r/9b12ad9e3a3f58/53584?app_id=2276"},{"Name":"Savvy","Tagline":"1-on-1 teaching and learning via live video","VotesCount":376,"RedirectUrl":"https://www.producthunt.com/r/2f5fe7da9d99b7/53577?app_id=2276"},{"Name":"Marker 2.0","Tagline":"Send badass screenshots to Slack, Trello, Github and more","VotesCount":280,"RedirectUrl":"https://www.producthunt.com/r/b4cb93c9a3cba6/53697?app_id=2276"},{"Name":"Keza","Tagline":"Wealthfront for your Bitcoin, investing for everyone.","VotesCount":295,"RedirectUrl":"https://www.producthunt.com/r/81ad5ac9e83188/53610?app_id=2276"},{"Name":"Spotify Fresh Finds","Tagline":"Like Hype Machine, but inside Spotify","VotesCount":231,"RedirectUrl":"https://www.producthunt.com/r/70c6dc6ac4199b/53705?app_id=2276"},{"Name":"Slate","Tagline":"Beautiful static documentation for your API","VotesCount":268,"RedirectUrl":"https://www.producthunt.com/r/234fb3bcaaba28/53632?app_id=2276"},{"Name":"Sketchsheets","Tagline":"Free device and web sketch sheets for Designers","VotesCount":221,"RedirectUrl":"https://www.producthunt.com/r/c1043cd292444e/53539?app_id=2276"},{"Name":"Product Hunt Giphy integration","Tagline":"Easiest way to enrich your PH comments with GIFs","VotesCount":175,"RedirectUrl":"https://www.producthunt.com/r/b0ef1822b60780/53649?app_id=2276"},{"Name":"Typeform LITE","Tagline":"Create beautiful interactive forms, surveys \u0026 more","VotesCount":162,"RedirectUrl":"https://www.producthunt.com/r/5c742118cc2de9/53677?app_id=2276"},{"Name":"WorkingOn 2.0","Tagline":"Minimalistic progress tracking for teams.","VotesCount":129,"RedirectUrl":"https://www.producthunt.com/r/9e489bcb8f9cb5/53756?app_id=2276"},{"Name":"Textografo","Tagline":"Create beautiful diagrams faster","VotesCount":162,"RedirectUrl":"https://www.producthunt.com/r/3325c0f59c6c2c/53500?app_id=2276"},{"Name":"Motion Sound","Tagline":"2100+ hand-crafted sounds for motion designers","VotesCount":125,"RedirectUrl":"https://www.producthunt.com/r/793d8d445c0e80/53606?app_id=2276"},{"Name":"TestSubject","Tagline":"Test how your email subject line displays on mobile devices.","VotesCount":119,"RedirectUrl":"https://www.producthunt.com/r/d9ccbed88b5072/53675?app_id=2276"},{"Name":"Monimen","Tagline":"Startup identification cards","VotesCount":109,"RedirectUrl":"https://www.producthunt.com/r/6e9af27b428bc8/53486?app_id=2276"},{"Name":"Dexter App Marketplace","Tagline":"Apps from SMS bots to podcast generators","VotesCount":120,"RedirectUrl":"https://www.producthunt.com/r/358dcd51000192/53642?app_id=2276"},{"Name":"Sleepfulness","Tagline":"The beautifully effective sleep app, powered by mindfulness.","VotesCount":104,"RedirectUrl":"https://www.producthunt.com/r/5f10c886884498/53574?app_id=2276"},{"Name":"Chill 2.0","Tagline":"A fast and fun way to communicate","VotesCount":196,"RedirectUrl":"https://www.producthunt.com/r/25d67aeb6c2c06/53650?app_id=2276"},{"Name":"dejavu","Tagline":"A modern, open-source data browser for Elasticsearch.","VotesCount":96,"RedirectUrl":"https://www.producthunt.com/r/1f82892b90eaa9/53760?app_id=2276"},{"Name":"FWD:Everyone","Tagline":"Your email inbox as a public blog","VotesCount":83,"RedirectUrl":"https://www.producthunt.com/r/c11eb02962b476/53729?app_id=2276"},{"Name":"Answers for tvOS","Tagline":"The #1 analytics solution for iOS, now supporting tvOS","VotesCount":76,"RedirectUrl":"https://www.producthunt.com/r/89f0b1af5c948a/53587?app_id=2276"},{"Name":"Reaction Story","Tagline":"Create your own reaction story","VotesCount":81,"RedirectUrl":"https://www.producthunt.com/r/bea591bd898b74/53540?app_id=2276"},{"Name":"Virtuali-Tee","Tagline":"T-Shirt that transforms into Virtual Reality learning ","VotesCount":68,"RedirectUrl":"https://www.producthunt.com/r/8f34b6b48304d6/53689?app_id=2276"},{"Name":"Showgo","Tagline":"Post comments at your exact moment in Netflix shows","VotesCount":114,"RedirectUrl":"https://www.producthunt.com/r/00d6d0ce4da411/53523?app_id=2276"},{"Name":"Outline Mail","Tagline":"Making HTML email ridiculously easy","VotesCount":65,"RedirectUrl":"https://www.producthunt.com/r/2611b27a017786/53554?app_id=2276"},{"Name":"The Modern Day Briefcase","Tagline":"Is it a backpack or a satchel?  It's both!","VotesCount":22,"RedirectUrl":"https://www.producthunt.com/r/28a73bcb5b5c55/53795?app_id=2276"},{"Name":"ClearFactr","Tagline":"Next-generation financial modeling","VotesCount":57,"RedirectUrl":"https://www.producthunt.com/r/2499ea5bf26637/53395?app_id=2276"},{"Name":"Meta 2 Dev Kit","Tagline":"The most immersive augmented reality on the planet","VotesCount":37,"RedirectUrl":"https://www.producthunt.com/r/4340811e76e402/53723?app_id=2276"},{"Name":"Agile Planner","Tagline":"Trello on steroids ","VotesCount":33,"RedirectUrl":"https://www.producthunt.com/r/fafeda34689bcf/53765?app_id=2276"},{"Name":"Staffjoy Boss","Tagline":"Automatically schedule your employees with AI","VotesCount":65,"RedirectUrl":"https://www.producthunt.com/r/c07956ad438d64/53663?app_id=2276"},{"Name":"Hands Free","Tagline":"Pay hands free with Google","VotesCount":32,"RedirectUrl":"https://www.producthunt.com/r/92414e590669c8/53758?app_id=2276"},{"Name":"GIF Brewery 3.0","Tagline":"Video to GIF creator","VotesCount":35,"RedirectUrl":"https://www.producthunt.com/r/d785fc192c154f/53654?app_id=2276"},{"Name":"SendRoll","Tagline":"Email Retargeting made easy","VotesCount":39,"RedirectUrl":"https://www.producthunt.com/r/8820575c901115/53755?app_id=2276"},{"Name":"Humanize","Tagline":"Strengthen your psychological immune system.","VotesCount":65,"RedirectUrl":"https://www.producthunt.com/r/739ea376977178/53661?app_id=2276"},{"Name":"CabinetM","Tagline":"Pinterest for marketing tools: find, compare and build stack","VotesCount":47,"RedirectUrl":"https://www.producthunt.com/r/87793eedec9a7f/53579?app_id=2276"},{"Name":"Mealime","Tagline":"Meal planning app with healthy meal plans","VotesCount":43,"RedirectUrl":"https://www.producthunt.com/r/98278f2b081a0e/53553?app_id=2276"},{"Name":"Bouncelytics","Tagline":"Finding website bottlenecks just got easier","VotesCount":30,"RedirectUrl":"https://www.producthunt.com/r/9708a25f186f96/53721?app_id=2276"},{"Name":"Yelp 3G","Tagline":"Yelp, without the stupid Internet.","VotesCount":28,"RedirectUrl":"https://www.producthunt.com/r/db6a0f954e19a8/53667?app_id=2276"},{"Name":"Fenix for Twitter","Tagline":"A fresh Twitter experience, for Android","VotesCount":34,"RedirectUrl":"https://www.producthunt.com/r/92acbee82fb386/53672?app_id=2276"},{"Name":"RecMix Recording App","Tagline":"Record, store and instantly share your music","VotesCount":35,"RedirectUrl":"https://www.producthunt.com/r/eca5c06ced8caf/52992?app_id=2276"},{"Name":"SoundShroud","Tagline":"De-clutter your SoundCloud stream. Get rid of those reposts.","VotesCount":34,"RedirectUrl":"https://www.producthunt.com/r/7626a1db3f9169/53585?app_id=2276"},{"Name":"Shnarped","Tagline":"Instagram for sports with amazing video-editing tools","VotesCount":76,"RedirectUrl":"https://www.producthunt.com/r/d1f7a075c9d116/53656?app_id=2276"},{"Name":"Pixelated Fireplace","Tagline":"Keeping you warm, digitally","VotesCount":20,"RedirectUrl":"https://www.producthunt.com/r/efe2241075ea21/53708?app_id=2276"},{"Name":"Frames","Tagline":"The best way to create videos with friends!","VotesCount":29,"RedirectUrl":"https://www.producthunt.com/r/e26aef8e98111f/53680?app_id=2276"},{"Name":"Spectrum Collage","Tagline":"Create collages based on color to share on instagram","VotesCount":27,"RedirectUrl":"https://www.producthunt.com/r/666f4118c749fd/53589?app_id=2276"}]}